{"description": "", "tags": [], "size": {"height": 512, "width": 640}, "objects": [{"description": "", "tags": [{"name": "Facade", "value": null}], "classTitle": "Facade", "points": {"exterior": [[4, 2], [8, 269], [38, 391], [41, 512], [254, 499], [249, 264], [398, 254], [418, 512], [640, 511], [637, 0]], "interior": []}}, {"description": "", "tags": [{"name": "Window", "value": null}], "classTitle": "Window", "points": {"exterior": [[408, 504], [395, 264], [223, 272], [219, 512]], "interior": []}}, {"description": "", "tags": [{"name": "Window", "value": null}], "classTitle": "Window", "points": {"exterior": [[42, 505], [19, 267], [0, 269], [0, 512]], "interior": []}}]}