{"description": "", "tags": [], "size": {"height": 512, "width": 640}, "objects": [{"description": "", "bitmap": null, "tags": [{"name": "Window", "value": null}], "classTitle": "Window", "points": {"exterior": [[330, 196], [549, 191], [561, 481], [311, 488]], "interior": []}}, {"description": "", "bitmap": null, "tags": [{"name": "Facade", "value": null}], "classTitle": "Facades", "points": {"exterior": [[2, 3], [638, 3], [639, 456], [562, 463], [560, 431], [559, 356], [556, 310], [557, 252], [550, 223], [547, 203], [536, 187], [453, 189], [363, 189], [331, 196], [325, 225], [329, 295], [314, 373], [311, 426], [310, 463], [306, 477], [150, 477], [39, 473], [0, 477]], "interior": []}}]}