{"description": "", "tags": [], "size": {"height": 512, "width": 640}, "objects": [{"description": "", "tags": [], "classTitle": "Facade", "points": {"exterior": [[0, 512], [640, 512], [640, 0], [0, 0]], "interior": []}}, {"description": "", "tags": [{"name": "Window", "value": null}], "classTitle": "Window", "points": {"exterior": [[147, 458], [148, 466], [151, 469], [157, 472], [302, 481], [331, 485], [377, 490], [419, 491], [435, 491], [450, 491], [462, 490], [466, 486], [467, 482], [471, 331], [475, 143], [471, 133], [457, 129], [445, 128], [269, 123], [155, 123], [149, 124], [145, 129], [143, 139]], "interior": []}}]}