{"description": "", "tags": [], "size": {"height": 512, "width": 640}, "objects": [{"description": "", "tags": [{"name": "Window", "value": null}], "classTitle": "Window", "points": {"exterior": [[249, 353], [230, 353], [224, 351], [220, 347], [218, 338], [218, 321], [218, 37], [219, 19], [225, 13], [238, 10], [259, 9], [495, 6], [516, 7], [522, 12], [523, 17], [523, 29], [518, 312], [516, 325], [512, 334], [506, 337], [472, 338]], "interior": []}}, {"description": "", "tags": [], "classTitle": "Facade", "points": {"exterior": [[0, 512], [640, 512], [640, 0], [0, 0]], "interior": []}}]}