{"description": "", "tags": [], "size": {"height": 512, "width": 640}, "objects": [{"description": "", "tags": [{"name": "Window", "value": null}], "classTitle": "Window", "points": {"exterior": [[128, 355], [96, 353], [92, 349], [89, 345], [87, 334], [87, 309], [83, 40], [86, 28], [94, 23], [111, 23], [375, 29], [386, 32], [390, 36], [390, 46], [386, 361], [384, 366], [380, 370], [371, 370]], "interior": []}}, {"description": "", "tags": [], "classTitle": "Facade", "points": {"exterior": [[0, 512], [640, 512], [640, 0], [0, 0]], "interior": []}}]}