{"description": "", "tags": [], "size": {"height": 512, "width": 640}, "objects": [{"description": "", "tags": [{"name": "Window", "value": null}], "classTitle": "Window", "points": {"exterior": [[194, 386], [164, 382], [159, 381], [155, 377], [152, 371], [152, 362], [152, 351], [149, 95], [149, 79], [153, 73], [159, 70], [174, 70], [413, 80], [429, 82], [434, 85], [437, 90], [437, 105], [432, 388], [431, 398], [429, 402], [425, 404], [420, 406], [413, 406]], "interior": []}}, {"description": "", "tags": [], "classTitle": "Facade", "points": {"exterior": [[0, 512], [640, 512], [640, 0], [0, 0]], "interior": []}}]}