{"description": "", "tags": [], "size": {"height": 512, "width": 640}, "objects": [{"description": "", "tags": [], "classTitle": "Facade", "points": {"exterior": [[130, 512], [508, 346], [511, 334], [508, 319], [511, 301], [511, 281], [514, 272], [507, 256], [507, 246], [497, 240], [489, 228], [484, 219], [473, 205], [466, 193], [460, 180], [461, 158], [471, 139], [489, 130], [511, 131], [525, 142], [537, 157], [560, 175], [568, 189], [579, 207], [585, 225], [594, 236], [594, 252], [596, 265], [596, 276], [591, 284], [591, 296], [598, 301], [604, 302], [640, 284], [640, 0], [561, 0], [357, 66], [133, 144], [0, 195], [0, 512]], "interior": []}}, {"description": "", "tags": [], "classTitle": "Roof", "points": {"exterior": [[626, 293], [155, 504], [640, 512]], "interior": []}}]}