{"description": "", "tags": [], "size": {"height": 512, "width": 640}, "objects": [{"description": "", "tags": [{"name": "Window", "value": null}], "classTitle": "Window", "points": {"exterior": [[243, 178], [239, 344], [409, 355], [410, 190]], "interior": []}}, {"description": "", "tags": [{"name": "Window", "value": null}], "classTitle": "Window", "points": {"exterior": [[640, 180], [596, 193], [595, 397], [640, 405]], "interior": []}}, {"description": "", "tags": [{"name": "Window", "value": null}], "classTitle": "Window", "points": {"exterior": [[6, 213], [69, 227], [68, 351], [0, 371]], "interior": []}}, {"description": "", "tags": [{"name": "Facade", "value": null}], "classTitle": "Facade", "points": {"exterior": [[0, 0], [0, 225], [72, 225], [71, 343], [232, 338], [240, 178], [406, 171], [415, 348], [588, 384], [601, 180], [640, 179], [640, 0]], "interior": []}}]}