{"description": "", "tags": [{"name": "Window", "value": null}], "size": {"height": 512, "width": 640}, "objects": [{"description": "", "tags": [{"name": "Facade", "value": null}], "classTitle": "Facade", "points": {"exterior": [[0, 0], [0, 512], [640, 512], [640, 0]], "interior": []}}, {"description": "", "tags": [{"name": "Window", "value": null}], "classTitle": "Window", "points": {"exterior": [[158, 94], [159, 307], [371, 319], [368, 91]], "interior": []}}, {"description": "", "tags": [{"name": "Window", "value": null}], "classTitle": "Window", "points": {"exterior": [[640, 89], [607, 91], [609, 311], [640, 322]], "interior": []}}]}