{"description": "", "tags": [{"name": "Window", "value": null}], "size": {"height": 512, "width": 640}, "objects": [{"description": "", "tags": [{"name": "Window", "value": null}], "classTitle": "Window", "points": {"exterior": [[232, 104], [226, 284], [399, 293], [404, 96]], "interior": []}}, {"description": "", "tags": [{"name": "Window", "value": null}], "classTitle": "Window", "points": {"exterior": [[636, 92], [611, 92], [610, 284], [640, 286]], "interior": []}}, {"description": "", "tags": [{"name": "Window", "value": null}], "classTitle": "Window", "points": {"exterior": [[604, 510], [615, 480], [640, 479], [640, 512]], "interior": []}}, {"description": "", "tags": [{"name": "Window", "value": null}], "classTitle": "Window", "points": {"exterior": [[407, 512], [400, 480], [230, 480], [225, 512]], "interior": []}}, {"description": "", "tags": [{"name": "Window", "value": null}], "classTitle": "Window", "points": {"exterior": [[27, 508], [16, 476], [0, 476], [0, 512]], "interior": []}}, {"description": "", "tags": [{"name": "Window", "value": null}], "classTitle": "Window", "points": {"exterior": [[0, 285], [23, 285], [25, 100], [0, 97]], "interior": []}}, {"description": "", "tags": [{"name": "Facade", "value": null}], "classTitle": "Facade", "points": {"exterior": [[0, 0], [0, 512], [640, 512], [640, 0]], "interior": []}}]}