{
    "description": "",
    "tags": [],
    "size": {
        "height": 512,
        "width": 640
    },
    "objects": [
        {
            "description": "",
            "geometryType": "polygon",
            "labelerLogin": "abiswas100",
            "tags": [],
            "classTitle": "Window",
            "points": {
                "exterior": [
                    [
                        179,
                        0
                    ],
                    [
                        175,
                        13
                    ],
                    [
                        586,
                        62
                    ],
                    [
                        610,
                        0
                    ]
                ],
                "interior": []
            }
        },
        {
            "description": "",
            "geometryType": "polygon",
            "labelerLogin": "abiswas100",
            "tags": [],
            "classTitle": "Window",
            "points": {
                "exterior": [
                    [
                        422,
                        272
                    ],
                    [
                        417,
                        324
                    ],
                    [
                        570,
                        330
                    ],
                    [
                        579,
                        273
                    ]
                ],
                "interior": []
            }
        },
        {
            "description": "",
            "geometryType": "polygon",
            "labelerLogin": "abiswas100",
            "tags": [],
            "classTitle": "Window",
            "points": {
                "exterior": [
                    [
                        285,
                        253
                    ],
                    [
                        295,
                        289
                    ],
                    [
                        207,
                        287
                    ],
                    [
                        196,
                        247
                    ]
                ],
                "interior": []
            }
        },
        {
            "description": "",
            "geometryType": "polygon",
            "labelerLogin": "abiswas100",
            "tags": [],
            "classTitle": "Ground",
            "points": {
                "exterior": [
                    [
                        0,
                        316
                    ],
                    [
                        0,
                        512
                    ],
                    [
                        640,
                        512
                    ],
                    [
                        640,
                        391
                    ]
                ],
                "interior": []
            }
        },
        {
            "description": "",
            "geometryType": "polygon",
            "labelerLogin": "abiswas100",
            "tags": [],
            "classTitle": "Facade",
            "points": {
                "exterior": [
                    [
                        0,
                        5
                    ],
                    [
                        0,
                        316
                    ],
                    [
                        640,
                        399
                    ],
                    [
                        640,
                        0
                    ]
                ],
                "interior": []
            }
        }
    ]
}