{
    "description": "",
    "tags": [],
    "size": {
        "height": 512,
        "width": 640
    },
    "objects": [
        {
            "description": "",
            "geometryType": "polygon",
            "labelerLogin": "debanjan",
            "tags": [],
            "classTitle": "Window",
            "points": {
                "exterior": [
                    [
                        145,
                        253
                    ],
                    [
                        412,
                        249
                    ],
                    [
                        402,
                        418
                    ],
                    [
                        165,
                        427
                    ]
                ],
                "interior": []
            }
        },
        {
            "description": "",
            "geometryType": "polygon",
            "labelerLogin": "debanjan",
            "tags": [],
            "classTitle": "Window",
            "points": {
                "exterior": [
                    [
                        170,
                        477
                    ],
                    [
                        178,
                        506
                    ],
                    [
                        397,
                        512
                    ],
                    [
                        391,
                        472
                    ]
                ],
                "interior": []
            }
        },
        {
            "description": "",
            "geometryType": "polygon",
            "labelerLogin": "debanjan",
            "tags": [],
            "classTitle": "Facade",
            "points": {
                "exterior": [
                    [
                        0,
                        2
                    ],
                    [
                        299,
                        2
                    ],
                    [
                        638,
                        131
                    ],
                    [
                        635,
                        507
                    ],
                    [
                        0,
                        507
                    ]
                ],
                "interior": []
            }
        }
    ]
}