{"description": "", "tags": [], "size": {"height": 512, "width": 640}, "objects": [{"description": "", "tags": [{"name": "Window", "value": null}], "classTitle": "Window", "points": {"exterior": [[580, 169], [573, 403], [332, 400], [342, 166]], "interior": []}}, {"description": "", "tags": [{"name": "Window", "value": null}], "classTitle": "Window", "points": {"exterior": [[172, 158], [182, 385], [0, 376], [0, 158]], "interior": []}}, {"description": "", "tags": [{"name": "Facade", "value": null}], "classTitle": "Facade", "points": {"exterior": [[633, 4], [639, 510], [2, 512], [0, 0]], "interior": []}}]}