{"description": "", "tags": [], "size": {"height": 512, "width": 640}, "objects": [{"description": "", "tags": [{"name": "Window", "value": null}], "classTitle": "Window", "points": {"exterior": [[0, 145], [170, 155], [181, 401], [0, 398]], "interior": []}}, {"description": "", "tags": [{"name": "Window", "value": null}], "classTitle": "Window", "points": {"exterior": [[264, 162], [256, 404], [466, 410], [473, 159]], "interior": []}}, {"description": "", "tags": [{"name": "Facade", "value": null}], "classTitle": "Facade", "points": {"exterior": [[636, 1], [639, 509], [0, 512], [5, 485], [122, 483], [121, 440], [2, 433], [0, 0]], "interior": []}}]}