{"description": "", "tags": [], "size": {"height": 512, "width": 640}, "objects": [{"description": "", "tags": [{"name": "Window", "value": null}], "classTitle": "Window", "points": {"exterior": [[72, 163], [67, 413], [286, 418], [287, 160]], "interior": []}}, {"description": "", "tags": [{"name": "Window", "value": null}], "classTitle": "Window", "points": {"exterior": [[378, 158], [376, 422], [597, 429], [598, 167]], "interior": []}}, {"description": "", "tags": [{"name": "Facade", "value": null}], "classTitle": "Facade", "points": {"exterior": [[638, 4], [639, 511], [233, 509], [231, 459], [135, 451], [128, 510], [0, 508], [0, 0]], "interior": []}}]}