{"description": "", "tags": [], "size": {"height": 512, "width": 640}, "objects": [{"description": "", "tags": [{"name": "Window", "value": null}], "classTitle": "Window", "points": {"exterior": [[3, 70], [193, 72], [187, 278], [7, 284]], "interior": []}}, {"description": "", "tags": [{"name": "Window", "value": null}], "classTitle": "Window", "points": {"exterior": [[310, 67], [311, 269], [503, 269], [509, 65]], "interior": []}}, {"description": "", "tags": [{"name": "Window", "value": null}], "classTitle": "Window", "points": {"exterior": [[485, 466], [488, 505], [309, 510], [312, 477]], "interior": []}}, {"description": "", "tags": [{"name": "Window", "value": null}], "classTitle": "Window", "points": {"exterior": [[201, 478], [204, 505], [24, 508], [26, 485]], "interior": []}}, {"description": "", "tags": [{"name": "Facade", "value": null}], "classTitle": "Facade", "points": {"exterior": [[0, 0], [1, 512], [640, 512], [640, 0]], "interior": []}}]}