{"description": "", "tags": [], "size": {"height": 512, "width": 640}, "objects": [{"description": "", "tags": [{"name": "Window", "value": null}], "classTitle": "Window", "points": {"exterior": [[151, 199], [152, 372], [313, 331], [315, 179]], "interior": []}}, {"description": "", "tags": [{"name": "Window", "value": null}], "classTitle": "Window", "points": {"exterior": [[392, 163], [384, 312], [522, 285], [526, 132]], "interior": []}}, {"description": "", "tags": [{"name": "Ground", "value": null}], "classTitle": "Ground", "points": {"exterior": [[639, 330], [61, 512], [640, 512]], "interior": []}}, {"description": "", "tags": [{"name": "Facade", "value": null}], "classTitle": "Facade", "points": {"exterior": [[637, 324], [63, 506], [0, 511], [0, 0], [640, 0]], "interior": []}}]}