{"description": "", "tags": [], "size": {"height": 512, "width": 640}, "objects": [{"description": "", "tags": [{"name": "Window", "value": null}], "classTitle": "Window", "points": {"exterior": [[11, 0], [11, 17], [167, 17], [164, 1]], "interior": []}}, {"description": "", "tags": [{"name": "Window", "value": null}], "classTitle": "Window", "points": {"exterior": [[10, 242], [14, 425], [173, 398], [167, 221]], "interior": []}}, {"description": "", "tags": [{"name": "Window", "value": null}], "classTitle": "Window", "points": {"exterior": [[342, 209], [344, 382], [484, 368], [485, 195]], "interior": []}}, {"description": "", "tags": [{"name": "Facade", "value": null}], "classTitle": "Facade", "points": {"exterior": [[0, 0], [0, 512], [640, 512], [638, 0]], "interior": []}}]}